OMGITSLACKO/__init__.py
OMGITSLACKO/functions.py
OMGITSLACKO/tozsdefunctions.py
OMGITSLACKO-0.1.11.dist-info/METADATA
OMGITSLACKO-0.1.11.dist-info/WHEEL
OMGITSLACKO-0.1.11.dist-info/top_level.txt
OMGITSLACKO-0.1.11.dist-info/RECORD
