Metadata-Version: 2.1
Name: OMGITSLACKO
Version: 0.1.11
Summary: A Python library for data analysis
Home-page: https://github.com/YOUR_USERNAME/OMGITSLACKO
Author: OMGITSLACKO
Author-email: solymarlaszlo1@gmail.com
License: MIT
Requires-Dist: pandas
Requires-Dist: numpy
